[1,["ecpdLyjvZBwrvm+cedCcQy","cf73jxyN9Jt47QTJU6ziYh","99FwsL0hBG8bITfZ4/IwmK","8855/VlrRKd6H0MSRnFxAU","675ovJ2tVK2aLYfgPUWOMv"],["node","_textureSetter","_spriteFrame","loadingBar","scene","_parent"],[["cc.Node",["_name","_id","_components","_contentSize","_trs","_parent","_children"],1,9,5,7,1,2],"cc.SpriteFrame",["cc.Sprite",["_type","_sizeMode","node","_materials","_spriteFrame"],1,1,3,6],["cc.SceneAsset",["_name","asyncLoadAssets"],1],["cc.Node",["_name","_parent","_children","_components","_contentSize","_trs"],2,1,2,12,5,7],["cc.Node",["_name","_parent","_components","_contentSize","_anchorPoint","_trs"],2,1,2,5,5,7],["cc.Canvas",["node","_designResolution"],3,1,5],["cc.Widget",["_alignFlags","node"],2,1],["52c90+EjzROYZbMmwiSpa5O",["node","loadingBar"],3,1,1],["cc.Scene",["_name","_children","_anchorPoint","_trs"],2,2,5,7],["cc.Camera",["_clearFlags","_depth","node"],1,1],["cc.ProgressBar",["_N$totalLength","_N$progress","node","_N$barSprite"],1,1,1],["cc.Label",["_string","_N$horizontalAlign","_N$verticalAlign","node","_materials"],0,1,3]],[[3,0,1,3],[0,0,1,6,2,3,4,3],[0,0,5,2,3,2],[0,0,5,2,3,4,2],[4,0,1,2,3,4,5,2],[5,0,1,2,3,4,5,2],[6,0,1,1],[7,0,1,2],[8,0,1,1],[2,0,1,2,3,4,3],[2,0,1,2,3,3],[9,0,1,2,3,2],[10,0,1,2,3],[11,0,1,2,3,3],[12,0,1,2,3,4,4]],[[[{"name":"default_progressbar","rect":[0,0,30,15],"offset":[0,0],"originalSize":[30,15],"capInsets":[10,4,10,4]}],[1],0,[0],[1],[1]],[[{"name":"default_progressbar_bg","rect":[0,0,60,15],"offset":[0,0],"originalSize":[60,15],"capInsets":[10,4,10,4]}],[1],0,[0],[1],[2]],[[[0,"Login",null],[1,"Canvas","a5esZu+45LA5mBpvttspPD",[-5,-6,-7],[[6,-1,[5,1080,1920]],[7,45,-2],[8,-4,-3]],[5,1080,1920],[540,960,0,0,0,0,1,1,1,1]],[4,"loadingBar",1,[-10],[[[9,1,0,-8,[1],2],-9],4,1],[5,600,15],[0,-713,0,0,0,0,1,1,1,1]],[11,"New Node",[1],[0,0,0],[0,0,0,0,0,0,1,1,1,1]],[2,"Main Camera",1,[[12,7,-1,-11]],[5,960,640]],[5,"bar",2,[-12],[5,0,15],[0,0,0.5],[-299.587,0,0,0,0,0,1,1,1,1]],[10,1,0,5,[0]],[13,600,0,2,6],[3,"New Label",1,[[14,"资源加载中...",1,1,-13,[3]]],[5,233.34,50.4],[0,-639.166,0,0,0,0,1,1,1,1]]],0,[0,0,1,0,0,1,0,3,7,0,0,1,0,-1,4,0,-2,2,0,-3,8,0,0,2,0,-2,7,0,-1,5,0,0,4,0,-1,6,0,0,8,0,4,3,1,5,3,13],[0,0,0,0,6],[-1,-1,2,-1,2],[0,0,3,0,4]]]]